controlUnit.vhd
-- //////////////////////////////
-- // Control Unit with timing //
-- //////////////////////////////

library ieee;
use ieee.std_logic_1164.all;
use ieee.numeric_std.all;

entity controlUnit is
    generic (
        -- Timing
        Tprop : time := 500 ps
    );
    port (
        -- Inputs
        instr : in std_logic_vector(31 downto 0);
        equal : in std_logic;
        
        -- IF control signals
        IF_PC_sel : out std_logic_vector(1 downto 0);
        
        -- EX control signals
        EX_ALU_sel_A : out std_logic;
        EX_ALU_sel_B : out std_logic;
        EX_sel_dst   : out std_logic_vector(1 downto 0);
        EX_ALU_Op    : out std_logic_vector(2 downto 0); 
        
        -- MEM control signals
        MEM_RAM_r_w : out std_logic;
        MEM_sel_wd  : out std_logic_vector(1 downto 0);

        -- WB control signals
        WB_RegWrite : out std_logic
    );
end controlUnit;

architecture timing of controlUnit is
    signal opcode : std_logic_vector(5 downto 0);
    signal funct : std_logic_vector(5 downto 0);

    signal PC_sel    : std_logic_vector(1 downto 0);
    signal ALU_sel_A : std_logic;
    signal ALU_sel_B : std_logic;
    signal sel_dst   : std_logic_vector(1 downto 0);
    signal ALU_Op    : std_logic_vector(2 downto 0); 
    signal RAM_r_w   : std_logic;
    signal sel_wd    : std_logic_vector(1 downto 0);
    signal RegWrite  : std_logic;

    -- FUNCT constants
    constant ADD  : std_logic_vector(5 downto 0) := "100000";
    constant ADDU : std_logic_vector(5 downto 0) := "100001";
    constant SLT  : std_logic_vector(5 downto 0) := "101010";
    constant JR   : std_logic_vector(5 downto 0) := "001000";
    constant LSL  : std_logic_vector(5 downto 0) := "000000";
    -- OPCODE constants
    constant R    : std_logic_vector(5 downto 0) := "000000";
    constant J    : std_logic_vector(5 downto 0) := "000010";
    constant JAL  : std_logic_vector(5 downto 0) := "000011";
    constant LW   : std_logic_vector(5 downto 0) := "100011";
    constant SW   : std_logic_vector(5 downto 0) := "101011";
    constant ADDi : std_logic_vector(5 downto 0) := "001000";
    constant SLTI : std_logic_vector(5 downto 0) := "001010";
    constant BEQ  : std_logic_vector(5 downto 0) := "000100";
    constant BNE  : std_logic_vector(5 downto 0) := "000101";

begin

    opcode <= instr(31 downto 26);
    funct  <= instr(5 downto 0);

    PC_sel <= "01" when opcode = J or opcode = JAL else
              "10" when (opcode = BEQ and equal = '1') or
                        (opcode = BNE and equal = '0') else
              "11" when (opcode = R and funct = JR) else
              "00";
    
    ALU_sel_A <= '1' when opcode = R and funct = LSL else
                 '0';

    ALU_sel_B <= '1' when opcode = LW or opcode = SW or
                          opcode = ADDI or opcode = SLTI else
                 '0';

    sel_dst <= "01" when opcode = R else
               "10" when opcode = JAL else
               "00";

    ALU_Op <= "001" when opcode = R and funct = LSL else
              "010" when opcode = R and funct = ADDU else
              "011" when (opcode = R and funct = ADD) or
                         opcode = LW or opcode = SW or
                         opcode = ADDI else
              "100" when (opcode = R and funct = SLT) or
                         opcode = SLTI else
              "000";

    RAM_r_w <= '1' when opcode = SW else
               '0';

    sel_wd <= "01" when opcode = LW else
              "10" when opcode = JAL else
              "00";

    RegWrite <= '1' when (opcode = R and (funct = ADD or
                            funct = ADDU or
                            funct = SLT or
                            funct = LSL)) or
                          opcode = JAL or
                          opcode = LW or
                          opcode = ADDI or
                          opcode = SLTI else
                '0';

    -- Timing
    IF_PC_sel    <= PC_sel    after Tprop;
    EX_ALU_sel_A <= ALU_sel_A after Tprop;
    EX_ALU_sel_B <= ALU_sel_B after Tprop;
    EX_sel_dst   <= sel_dst   after Tprop;
    EX_ALU_Op    <= ALU_Op    after Tprop;
    MEM_RAM_r_w  <= RAM_r_w   after Tprop;
    MEM_sel_wd   <= sel_wd    after Tprop;
    WB_RegWrite  <= RegWrite  after Tprop;
end;

controlUnit_tb.vhd
library ieee;
use ieee.std_logic_1164.all;

entity controlUnit_tb is
end entity;

architecture behavior of controlUnit_tb is

	component controlUnit is
		generic (
			-- Timing
			Tprop : time := 500 ps
		);
		port (
			-- Inputs
			instr : in std_logic_vector(31 downto 0);
			equal : in std_logic;
			
			-- IF control signals
			IF_PC_sel : out std_logic_vector(1 downto 0);
			
			-- EX control signals
			EX_ALU_sel_A : out std_logic;
			EX_ALU_sel_B : out std_logic;
			EX_sel_dst   : out std_logic_vector(1 downto 0);
			EX_ALU_Op    : out std_logic_vector(2 downto 0); 
			
			-- MEM control signals
			MEM_RAM_r_w : out std_logic;
			MEM_sel_wd  : out std_logic_vector(1 downto 0);
	
			-- WB control signals
			WB_RegWrite : out std_logic
		);
	end component;

	signal instr : std_logic_vector(31 downto 0);
	signal equal :  std_logic;
	signal IF_PC_sel :  std_logic_vector(1 downto 0);
	signal EX_ALU_sel_A : std_logic;
	signal EX_ALU_sel_B : std_logic;
	signal EX_sel_dst   : std_logic_vector(1 downto 0);
	signal EX_ALU_Op    : std_logic_vector(2 downto 0); 
	signal MEM_RAM_r_w : std_logic;
	signal MEM_sel_wd  : std_logic_vector(1 downto 0);
	signal WB_RegWrite : std_logic;

begin

	uut: controlUnit port map (
		instr        => instr,        
		equal        => equal,       
		IF_PC_sel    => IF_PC_sel,    
		EX_ALU_sel_A => EX_ALU_sel_A, 
		EX_ALU_sel_B => EX_ALU_sel_B, 
		EX_sel_dst   => EX_sel_dst,   
		EX_ALU_Op    => EX_ALU_Op,    
		MEM_RAM_r_w  => MEM_RAM_r_w,  
		MEM_sel_wd   => MEM_sel_wd,   
		WB_RegWrite  => WB_RegWrite  
	);

	
	process
	begin
		equal <= '0';
		-- 100011 LW
		instr <= X"8C000000";
		wait for 10 ns;
		-- 101011 SW
		instr <= X"AC000000";
		wait for 10 ns;
		-- 001000 ADDI
		instr <= X"20000000";
		wait for 10 ns;
		-- 000100 BEQ
		instr <= X"10000000";
		wait for 5 ns;
		equal <= '1';
		wait for 5 ns;
		equal <= '0';
		-- 001010 SLTI
		instr <= X"28000000";
		wait for 10 ns;
		-- 000101 BNE
		instr <= X"14000000";
		wait for 5 ns;
		equal <= '1';
		wait for 5 ns;
		equal <= '0';
		-- 100000 ADD
		instr <= X"00000020";
		wait for 10 ns;
		-- 101010 SLT
		instr <= X"0000002A";
		wait for 10 ns;
		-- 001000 JR
		instr <= X"00000008";
		wait for 10 ns;
		-- 100001 ADDU
		instr <= X"00000021";
		wait for 10 ns;
		-- 000000 SLL
		instr <= X"00000000";
		wait for 10 ns;
		-- 000010 J
		instr <= X"08000000";
		wait for 10 ns;
		-- 000011 JAL
		instr <= X"0C000000";
		wait for 10 ns;
		wait;
	end process;

 end architecture;

controlUnit_tb.vcd
$date
  Sun Jul 12 20:10:20 2020
$end
$version
  GHDL v0
$end
$timescale
  1 fs
$end
$scope module standard $end
$upscope $end
$scope module std_logic_1164 $end
$upscope $end
$scope module numeric_std $end
$upscope $end
$scope module controlunit_tb $end
$var reg 32 ! instr[31:0] $end
$var reg 1 " equal $end
$var reg 2 # if_pc_sel[1:0] $end
$var reg 1 $ ex_alu_sel_a $end
$var reg 1 % ex_alu_sel_b $end
$var reg 2 & ex_sel_dst[1:0] $end
$var reg 3 ' ex_alu_op[2:0] $end
$var reg 1 ( mem_ram_r_w $end
$var reg 2 ) mem_sel_wd[1:0] $end
$var reg 1 * wb_regwrite $end
$scope module uut $end
$var reg 32 + instr[31:0] $end
$var reg 1 , equal $end
$var reg 2 - if_pc_sel[1:0] $end
$var reg 1 . ex_alu_sel_a $end
$var reg 1 / ex_alu_sel_b $end
$var reg 2 0 ex_sel_dst[1:0] $end
$var reg 3 1 ex_alu_op[2:0] $end
$var reg 1 2 mem_ram_r_w $end
$var reg 2 3 mem_sel_wd[1:0] $end
$var reg 1 4 wb_regwrite $end
$var reg 6 5 opcode[5:0] $end
$var reg 6 6 funct[5:0] $end
$var reg 2 7 pc_sel[1:0] $end
$var reg 1 8 alu_sel_a $end
$var reg 1 9 alu_sel_b $end
$var reg 2 : sel_dst[1:0] $end
$var reg 3 ; alu_op[2:0] $end
$var reg 1 < ram_r_w $end
$var reg 2 = sel_wd[1:0] $end
$var reg 1 > regwrite $end
$upscope $end
$upscope $end
$enddefinitions $end
#0
b10001100000000000000000000000000 !
0"
bUU #
U$
U%
bUU &
bUUU '
U(
bUU )
U*
b10001100000000000000000000000000 +
0,
bUU -
U.
U/
bUU 0
bUUU 1
U2
bUU 3
U4
b100011 5
b000000 6
b00 7
08
19
b00 :
b011 ;
0<
b01 =
1>
#500000
b00 #
0$
1%
b00 &
b011 '
0(
b01 )
1*
b00 -
0.
1/
b00 0
b011 1
02
b01 3
14
#10000000
b10101100000000000000000000000000 !
b10101100000000000000000000000000 +
b101011 5
1<
b00 =
0>
#10500000
1(
b00 )
0*
12
b00 3
04
#20000000
b00100000000000000000000000000000 !
b00100000000000000000000000000000 +
b001000 5
0<
1>
#20500000
0(
1*
02
14
#30000000
b00010000000000000000000000000000 !
b00010000000000000000000000000000 +
b000100 5
09
b000 ;
0>
#30500000
0%
b000 '
0*
0/
b000 1
04
#35000000
1"
1,
b10 7
#35500000
b10 #
b10 -
#40000000
b00101000000000000000000000000000 !
0"
b00101000000000000000000000000000 +
0,
b001010 5
b00 7
19
b100 ;
1>
#40500000
b00 #
1%
b100 '
1*
b00 -
1/
b100 1
14
#50000000
b00010100000000000000000000000000 !
b00010100000000000000000000000000 +
b000101 5
b10 7
09
b000 ;
0>
#50500000
b10 #
0%
b000 '
0*
b10 -
0/
b000 1
04
#55000000
1"
1,
b00 7
#55500000
b00 #
b00 -
#60000000
b00000000000000000000000000100000 !
0"
b00000000000000000000000000100000 +
0,
b000000 5
b100000 6
b00 7
b01 :
b011 ;
1>
#60500000
b01 &
b011 '
1*
b00 -
b01 0
b011 1
14
#70000000
b00000000000000000000000000101010 !
b00000000000000000000000000101010 +
b101010 6
b100 ;
#70500000
b100 '
b100 1
#80000000
b00000000000000000000000000001000 !
b00000000000000000000000000001000 +
b001000 6
b11 7
b000 ;
0>
#80500000
b11 #
b000 '
0*
b11 -
b000 1
04
#90000000
b00000000000000000000000000100001 !
b00000000000000000000000000100001 +
b100001 6
b00 7
b010 ;
1>
#90500000
b00 #
b010 '
1*
b00 -
b010 1
14
#100000000
b00000000000000000000000000000000 !
b00000000000000000000000000000000 +
b000000 6
18
b001 ;
#100500000
1$
b001 '
1.
b001 1
#110000000
b00001000000000000000000000000000 !
b00001000000000000000000000000000 +
b000010 5
b01 7
08
b00 :
b000 ;
0>
#110500000
b01 #
0$
b00 &
b000 '
0*
b01 -
0.
b00 0
b000 1
04
#120000000
b00001100000000000000000000000000 !
b00001100000000000000000000000000 +
b000011 5
b10 :
b10 =
1>
#120500000
b10 &
b10 )
1*
b10 0
b10 3
14
