mux_4x1.vhd
-- /////////////////////////////////
-- // 4x1 Multiplexer with timing //
-- /////////////////////////////////

library ieee;
use ieee.std_logic_1164.all;
use ieee.numeric_std.all;

entity mux_4x1 is
    generic (
        wordSize : natural := 32;
        -- Timing
        Tsel  : time := 500 ps;
        Tdata : time := 250 ps 
    );
    port (
        in0 : in  std_logic_vector(wordSize-1 downto 0);
        in1 : in  std_logic_vector(wordSize-1 downto 0);
        in2 : in  std_logic_vector(wordSize-1 downto 0);
        in3 : in  std_logic_vector(wordSize-1 downto 0);
        sel : in  std_logic_vector(1 downto 0);
        res : out std_logic_vector(wordSize-1 downto 0)
    );
end mux_4x1;

architecture timing of mux_4x1 is
begin
    with sel select res <=
        in0 after Tsel when "00",
        in1 after Tsel when "01",
        in2 after Tsel when "10",
        in3 after Tsel when "11",
        (others => 'X') when others;
end timing;

mux_4x1_tb.vhd
library ieee;
use ieee.std_logic_1164.all;
use ieee.numeric_std.all;

entity mux_4x1_tb is
end entity;

architecture tb of mux_4x1_tb is

    component mux_4x1 is
        generic (
            wordSize : natural := 32;
            -- Timing
            Tsel  : time := 500 ps;
            Tdata : time := 250 ps 
        );
        port (
            in0 : in  std_logic_vector(wordSize-1 downto 0);
            in1 : in  std_logic_vector(wordSize-1 downto 0);
            in2 : in  std_logic_vector(wordSize-1 downto 0);
            in3 : in  std_logic_vector(wordSize-1 downto 0);
            sel : in  std_logic_vector(1 downto 0);
            res : out std_logic_vector(wordSize-1 downto 0)
        );
    end component;

    signal in0, in1, in2, in3, res : std_logic_vector(31 downto 0);
    signal sel : std_logic_vector(1 downto 0);

begin

    uut: mux_4x1 port map (in0, in1, in2, in3, sel, res);

    process
    begin
        report "BOT";

        in0 <= x"000000FF";
        in1 <= x"0000FF00";
        in2 <= x"00FF0000";
        in3 <= x"FF000000";

        -- Test 1
        sel <= "00";
        wait for 500 ps;
        assert(res = in0) report "Test 1 failed." severity error;
        wait for 500 ps;

        -- Test 2
        sel <= "01";
        wait for 500 ps;
        assert(res = in1) report "Test 2 failed." severity error;
        wait for 500 ps;

        -- Test 3
        sel <= "10";
        wait for 500 ps;
        assert(res = in2) report "Test 3 failed." severity error;
        wait for 500 ps;

        -- Test 4
        sel <= "11";
        wait for 500 ps;
        assert(res = in3) report "Test 4 failed." severity error;
        wait for 500 ps;

        report "EOT";
        wait;
    end process;

end tb;

mux_4x1_tb.vcd
$date
  Sat Jul 11 19:53:51 2020
$end
$version
  GHDL v0
$end
$timescale
  1 fs
$end
$scope module standard $end
$upscope $end
$scope module std_logic_1164 $end
$upscope $end
$scope module numeric_std $end
$upscope $end
$scope module mux_4x1_tb $end
$var reg 32 ! in0[31:0] $end
$var reg 32 " in1[31:0] $end
$var reg 32 # in2[31:0] $end
$var reg 32 $ in3[31:0] $end
$var reg 32 % res[31:0] $end
$var reg 2 & sel[1:0] $end
$scope module uut $end
$var reg 32 ' in0[31:0] $end
$var reg 32 ( in1[31:0] $end
$var reg 32 ) in2[31:0] $end
$var reg 32 * in3[31:0] $end
$var reg 2 + sel[1:0] $end
$var reg 32 , res[31:0] $end
$upscope $end
$upscope $end
$enddefinitions $end
#0
b00000000000000000000000011111111 !
b00000000000000001111111100000000 "
b00000000111111110000000000000000 #
b11111111000000000000000000000000 $
bXXXXXXXXXXXXXXXXXXXXXXXXXXXXXXXX %
b00 &
b00000000000000000000000011111111 '
b00000000000000001111111100000000 (
b00000000111111110000000000000000 )
b11111111000000000000000000000000 *
b00 +
bXXXXXXXXXXXXXXXXXXXXXXXXXXXXXXXX ,
#500000
b00000000000000000000000011111111 %
b00000000000000000000000011111111 ,
#1000000
b01 &
b01 +
#1500000
b00000000000000001111111100000000 %
b00000000000000001111111100000000 ,
#2000000
b10 &
b10 +
#2500000
b00000000111111110000000000000000 %
b00000000111111110000000000000000 ,
#3000000
b11 &
b11 +
#3500000
b11111111000000000000000000000000 %
b11111111000000000000000000000000 ,
