reg.vhd
-- //////////////////////////////////
-- // Generic Register with timing //
-- //////////////////////////////////

library ieee;
use ieee.std_logic_1164.all;
use ieee.numeric_std.all;

entity reg is
	generic (
		size:	natural := 32;
        def:	natural := 0;
        -- Timing
		Tsetup:	time := 250 ps;
		Tprop:	time := 1000 ps
	);
	port (
		D : in  std_logic_vector(size - 1 downto 0);
		Q :	out std_logic_vector(size - 1 downto 0);
		clk, ce, rst : in std_logic
	);
end entity;

architecture save of reg is
	signal Qi: std_logic_vector(size - 1 downto 0) := std_logic_vector(to_unsigned(def, size));
begin

	process(clk, rst)
	begin
		if rst = '1' then
			Qi <= std_logic_vector(to_unsigned(def, size));
		elsif rising_edge(clk) and ce = '1' then 
            if (D'last_event < Tsetup) then
                report "Tsetup violation in reg.";
                Qi <= (others => 'X');
            else
                Qi <= D;
			end if;
		end if;
	end process;

	Q <= Qi after Tprop;
end architecture;

reg_tb.vhd
library ieee;
use ieee.std_logic_1164.all;
use ieee.numeric_std.all;

entity reg_tb is
end reg_tb;

architecture tb of reg_tb is
    component reg is
        generic (
            size:	natural := 32;
            def:	natural := 0;
            -- Timing
            Tsetup:	time := 250 ps;
            Tprop:	time := 1000 ps
        );
        port (
            D : in  std_logic_vector(size - 1 downto 0);
            Q :	out std_logic_vector(size - 1 downto 0);
            clk, ce, rst : in std_logic
        );
    end component;

    signal D, Q : std_logic_vector(31 downto 0);
    signal clk, rst, ce : std_logic;
    signal simulating : std_logic;
    
begin
    
    uut: reg port map (D, Q, clk, ce, rst);

    clock: process
    begin
        clk <= '0';
        wait for 5 ns;
        clk <= '1';
        wait for 5 ns;

        if (simulating = '0') then
            wait;
        end if;
    end process;

    tests: process
    begin
        report "BOT";
        simulating <= '1';
        rst <= '0';
        ce <= '1';
        
        -- normal operation
        D <= x"000000AB";
        wait for 6 ns;
        assert(Q = D) report "Q is wrong." severity error;
        
        -- violate Tsetup
        wait for 8 ns;
        wait for 850 ps;
        D <= x"0000FFFF";
        wait for 150 ps;
        wait for 15 ns;
        simulating <= '0';
        report "EOT";
        wait;
    end process;
end tb;

reg_tb.vcd
$date
  Sat Jul 11 16:42:03 2020
$end
$version
  GHDL v0
$end
$timescale
  1 fs
$end
$scope module standard $end
$upscope $end
$scope module std_logic_1164 $end
$upscope $end
$scope module numeric_std $end
$upscope $end
$scope module reg_tb $end
$var reg 32 ! d[31:0] $end
$var reg 32 " q[31:0] $end
$var reg 1 # clk $end
$var reg 1 $ rst $end
$var reg 1 % ce $end
$var reg 1 & simulating $end
$scope module uut $end
$var reg 32 ' d[31:0] $end
$var reg 32 ( q[31:0] $end
$var reg 1 ) clk $end
$var reg 1 * ce $end
$var reg 1 + rst $end
$var reg 32 , qi[31:0] $end
$upscope $end
$upscope $end
$enddefinitions $end
#0
b00000000000000000000000010101011 !
bUUUUUUUUUUUUUUUUUUUUUUUUUUUUUUUU "
0#
0$
1%
1&
b00000000000000000000000010101011 '
bUUUUUUUUUUUUUUUUUUUUUUUUUUUUUUUU (
0)
1*
0+
b00000000000000000000000000000000 ,
#1000000
b00000000000000000000000000000000 "
b00000000000000000000000000000000 (
#5000000
1#
1)
b00000000000000000000000010101011 ,
#6000000
b00000000000000000000000010101011 "
b00000000000000000000000010101011 (
#10000000
0#
0)
#14000000
#14850000
b00000000000000001111111111111111 !
b00000000000000001111111111111111 '
#15000000
1#
1)
bXXXXXXXXXXXXXXXXXXXXXXXXXXXXXXXX ,
#16000000
bXXXXXXXXXXXXXXXXXXXXXXXXXXXXXXXX "
bXXXXXXXXXXXXXXXXXXXXXXXXXXXXXXXX (
#20000000
0#
0)
#25000000
1#
1)
b00000000000000001111111111111111 ,
#26000000
b00000000000000001111111111111111 "
b00000000000000001111111111111111 (
#30000000
0#
0&
0)
