regfile.vhd
-- /////////////////////////
-- // Regfile with timing //
-- /////////////////////////

library ieee;
use ieee.std_logic_1164.all;
use ieee.numeric_std.all;

entity regfile is
    generic (
        -- Timing
        Tread  : time := 4000 ps;
        Twrite : time := 4000 ps
    );
    port (
        Read1, Read2 : in std_logic_vector(4 downto 0);
        Write1       : in std_logic_vector(4 downto 0);
        WriteData    : in std_logic_vector(31 downto 0);
        RegWrite, rst, clk : in std_logic;
        Data1, Data2  : out std_logic_vector(31 downto 0)
    );
end regfile;

architecture timing of regfile is
    type bank_type is array (31 downto 0) of std_logic_vector(31 downto 0);
    signal data: bank_type;

    signal aux1, aux2, waux : std_logic_vector(31 downto 0);

begin
    process (clk, rst)
	begin
		if rst = '1' then 
			data <= (others => (others => '0'));
			data(28) <= X"00000200";
			data(29) <= X"0000FFFF";
		elsif rising_edge(clk) then 
			if RegWrite = '1' and Write1 /= "00000" then
				data(to_integer(unsigned(Write1))) <= WriteData after Twrite;
			end if;
		end if;
	end process;

	aux1 <= data(to_integer(unsigned(Read1)));
	aux2 <= data(to_integer(unsigned(Read2)));

	Data1 <= aux1 after Tread;
	Data2 <= aux2 after Tread;

end timing;

regfile_tb.vhd
library ieee;
use ieee.std_logic_1164.all;
use ieee.numeric_std.all;

entity regfile_tb is
end entity;

architecture tb of regfile_tb is
    component regfile is
        generic (
            -- Timing
            Tread  : time := 4000 ps;
            Twrite : time := 4000 ps
        );
        port (
            Read1, Read2 : in std_logic_vector(4 downto 0);
            Write1       : in std_logic_vector(4 downto 0);
            WriteData    : in std_logic_vector(31 downto 0);
            RegWrite, rst, clk : in std_logic;
            Data1, Data2  : out std_logic_vector(31 downto 0)
        );
    end component;

    signal Read1, Read2, Write1 : std_logic_vector(4 downto 0) := "00000";
    signal Data1, Data2, WriteData : std_logic_vector(31 downto 0);
    signal RegWrite, rst, clk : std_logic;
    signal simulating : bit;

begin

    uut: regfile port map (Read1, Read2, Write1, WriteData,RegWrite, rst,
        clk, Data1, Data2);

    clock: process
    begin
        clk <= '0';
        wait for 10 ns;
        clk <= '1';
        wait for 10 ns;

        if (simulating = '0') then
            wait;
        end if;
    end process;

    tests: process
    begin
        report "BOT.";
        simulating <= '1';
        Read1 <= "00000";
        Read2 <= "00001";
        Write1 <= "00001";
        WriteData <= x"00FF00AB";
        RegWrite <= '0';

        -- reset
        rst <= '1';
        wait for 5 ns;
        rst <= '0';

        -- Test 1: read value;
        wait for 5 ns;
        Read1 <= "11101";
        wait for 4 ns;
        assert(Data1 = x"0000ffff") report "Test 1 fail" severity error;

        -- Test 2: write value;
        wait until falling_edge(clk);
        RegWrite <= '1';
        wait until rising_edge(clk);
        wait for 8 ns;
        assert(Data2 = x"00FF00AB") report "Test 2 fail" severity error;

        -- Test 3: write on zero
        wait until falling_edge(clk);
        Write1 <= "00000";
        Read1 <= "00000";
        wait until rising_edge(clk);
        wait for 8 ns;
        assert(Data1 = x"00000000") report "Test 3 fail" severity error;

        simulating <= '0';
        report "EOT.";
        wait;
    end process;
end architecture;

regfile_tb.vcd
$date
  Sun Jul 12 01:27:19 2020
$end
$version
  GHDL v0
$end
$timescale
  1 fs
$end
$scope module standard $end
$upscope $end
$scope module std_logic_1164 $end
$upscope $end
$scope module numeric_std $end
$upscope $end
$scope module regfile_tb $end
$var reg 5 ! read1[4:0] $end
$var reg 5 " read2[4:0] $end
$var reg 5 # write1[4:0] $end
$var reg 32 $ data1[31:0] $end
$var reg 32 % data2[31:0] $end
$var reg 32 & writedata[31:0] $end
$var reg 1 ' regwrite $end
$var reg 1 ( rst $end
$var reg 1 ) clk $end
$var reg 1 * simulating $end
$scope module uut $end
$var reg 5 + read1[4:0] $end
$var reg 5 , read2[4:0] $end
$var reg 5 - write1[4:0] $end
$var reg 32 . writedata[31:0] $end
$var reg 1 / regwrite $end
$var reg 1 0 rst $end
$var reg 1 1 clk $end
$var reg 32 2 data1[31:0] $end
$var reg 32 3 data2[31:0] $end
$comment data is not handled $end
$var reg 32 4 aux1[31:0] $end
$var reg 32 5 aux2[31:0] $end
$var reg 32 6 waux[31:0] $end
$upscope $end
$upscope $end
$enddefinitions $end
#0
b00000 !
b00001 "
b00001 #
bUUUUUUUUUUUUUUUUUUUUUUUUUUUUUUUU $
bUUUUUUUUUUUUUUUUUUUUUUUUUUUUUUUU %
b00000000111111110000000010101011 &
0'
1(
0)
1*
b00000 +
b00001 ,
b00001 -
b00000000111111110000000010101011 .
0/
10
01
bUUUUUUUUUUUUUUUUUUUUUUUUUUUUUUUU 2
bUUUUUUUUUUUUUUUUUUUUUUUUUUUUUUUU 3
b00000000000000000000000000000000 4
b00000000000000000000000000000000 5
bUUUUUUUUUUUUUUUUUUUUUUUUUUUUUUUU 6
#4000000
b00000000000000000000000000000000 $
b00000000000000000000000000000000 %
b00000000000000000000000000000000 2
b00000000000000000000000000000000 3
#5000000
0(
00
#10000000
b11101 !
1)
b11101 +
11
b00000000000000001111111111111111 4
#14000000
b00000000000000001111111111111111 $
b00000000000000001111111111111111 2
#20000000
1'
0)
1/
01
#30000000
1)
11
#34000000
b00000000111111110000000010101011 5
#38000000
b00000000111111110000000010101011 %
b00000000111111110000000010101011 3
#40000000
b00000 !
b00000 #
0)
b00000 +
b00000 -
01
b00000000000000000000000000000000 4
#44000000
b00000000000000000000000000000000 $
b00000000000000000000000000000000 2
#50000000
1)
11
#58000000
0*
